odoo10_addon_account_move_chatter-10.0.1.0.0.99.dev2-py3.8-nspkg.pth
odoo/addons/account_move_chatter/README.rst
odoo/addons/account_move_chatter/__init__.py
odoo/addons/account_move_chatter/__manifest__.py
odoo/addons/account_move_chatter/i18n/account_move_chatter.pot
odoo/addons/account_move_chatter/i18n/es.po
odoo/addons/account_move_chatter/i18n/pt.po
odoo/addons/account_move_chatter/models/__init__.py
odoo/addons/account_move_chatter/models/account_move.py
odoo/addons/account_move_chatter/readme/CONFIGURE.rst
odoo/addons/account_move_chatter/readme/CONTRIBUTORS.rst
odoo/addons/account_move_chatter/readme/DESCRIPTION.rst
odoo/addons/account_move_chatter/readme/USAGE.rst
odoo/addons/account_move_chatter/static/description/icon.png
odoo/addons/account_move_chatter/static/description/index.html
odoo/addons/account_move_chatter/views/account_move_views.xml
odoo10_addon_account_move_chatter-10.0.1.0.0.99.dev2.dist-info/METADATA
odoo10_addon_account_move_chatter-10.0.1.0.0.99.dev2.dist-info/WHEEL
odoo10_addon_account_move_chatter-10.0.1.0.0.99.dev2.dist-info/namespace_packages.txt
odoo10_addon_account_move_chatter-10.0.1.0.0.99.dev2.dist-info/top_level.txt
odoo10_addon_account_move_chatter-10.0.1.0.0.99.dev2.dist-info/RECORD
